{
"title":"将进酒",
"poem":"君不见黄河之水天上来，奔流到海不复回。君不见高堂明镜悲白发，朝如青丝暮成雪。人生得意须尽欢，莫使金樽空对月。天生我材必有用，千金散尽还复来。烹羊宰牛且为乐，会须一饮三百杯。岑夫子，丹丘生，将进酒，杯莫停。与君歌一曲，请君为我倾耳听。(倾耳听 一作：侧耳听)钟鼓馔玉不足贵，但愿长醉不愿醒。(不足贵 一作：何足贵；不愿醒 一作：不复醒)古来圣贤皆寂寞，惟有饮者留其名。(古来 一作：自古；惟 通：唯)陈王昔时宴平乐，斗酒十千恣欢谑。主人何为言少钱，径须沽取对君酌。五花马、千金裘，呼儿将出换美酒，与尔同销万古愁。",
"description":"译文你难道没有看见吗？那黄河之水犹如从天上倾泻而来，波涛翻滚直奔东海从来不会再往回流。你难道没有看见，在高堂上面对明镜，深沉悲叹那一头白发？早晨还是青丝到了傍晚却变得如雪一般。人生得意之时就要尽情的享受欢乐，不要让金杯无酒空对皎洁的明月。上天造就了我的才干就必然是有用处的，千两黄金花完了也能够再次获得。且把烹煮羔羊和宰牛当成一件快乐的事情，如果需要也应当痛快地喝三百杯。岑勋，元丹丘，快点喝酒，不要停下来。我给你们唱一首歌，请你们为我倾耳细听。山珍海味的豪华生活算不上什么珍贵，只希望能醉生梦死而",
"extension1":"创作背景",
"extension2":"关于这首诗的写作时间，说法不一。郁贤皓《李白集》认为此诗约作于开元二十四年（公元736年）前后。黄锡珪《李太白编年诗集目录》系于天宝十一载（752）。一般认为这是李白天宝年间离京后，漫游梁、宋，与友人岑勋、元丹丘相会时所作。"
}
