{
"title":"柳梢青·岳阳楼",
"poem":"袖剑飞吟。洞庭青草，秋水深深。万顷波光，岳阳楼上，一快披襟。不须携酒登临。问有酒、何人共斟？变尽人间，君山一点，自古如今。",
"description":"译文带着短剑到处歌吟，洞庭湖和青草湖，明净的秋水深又深。在雄伟的岳阳楼上，眺望万顷粼粼波光，迎着西风敞开衣襟。用不着带酒登上高楼，问你有酒又与谁共斟？人世间的事不停变幻，只有湖中那一点君山，依然故我，自古如今。",
"extension1":"这是一首登临遣怀之作。",
"extension2":"“袖剑飞吟”，据《唐才子传》记载，吕洞宾尝饮岳阳楼，醉后留诗曰：“朝游南浦暮苍梧，袖里青蛇胆气粗。三入岳阳人不识，朗吟飞过洞庭湖”。词人浪迹南北，与吕洞宾诗中所表现的气质有共通之处。这里借用来抒发自己壮游洞庭的情怀，一开始就树立了一个飘泊江湖的词人形象，并使词篇笼罩在豪迈飘逸的仙气中。“洞庭青草，秋水深深”，八百里洞庭以浩瀚汪洋著称，这里词人只用“深深”二字，便轻轻描绘出它的特征。词篇至此，气象也更为开阔。此外，句中的“秋”字不单点明登楼时令，还以秋日多风和入秋百卉渐衰为下文“一快披襟”、“变尽人间”作铺垫，同时又与词人的苍凉胸怀相表里。“"
}
