{
"title":"谒金门·花过雨",
"poem":"花过雨，又是一番红素。燕子归来愁不语，旧巢无觅处。谁在玉关劳苦？谁在玉楼歌舞？若使胡尘吹得去，东风侯万户。",
"description":"译文花经过一场春雨后，渐渐的开放了，燕子从北方飞回到这里因为找不到旧时的巢穴而愁楚。是谁在边关前线戍守？又是谁在玉楼里莺歌燕舞？假如东风能吹走侵略的敌人，那就封它做个万户侯吧！",
"extension1":"在诗词中常将春和雨以及花和雨联系起来。不过由于时间与气候的变化，有的风雨是送春归，有的风雨则是催春来。而李好古的这首词说：“花过雨，又是一番红素”。大概是属于催春来。“燕子归来愁不语”一句，承上启下，春来燕归，春色依旧，而归来的燕子为什么却闷闷无语呢？自然引出下文——“旧巢无觅处”。“旧巢无觅处”的原因，作者没有直说，犹露犹藏发人深思。这首词有的本调名下有题——《怀故居》，因而有人说，燕子旧巢，比喻自己故居，春来到来了，人无归处，表现了一种无处可归的飘泊之感。其中还寓有家国之感，所以把它理解为那个特定社会现象的典型概括，则更为合适。上片结句，就字面看补足了上文，完成了对“燕子”的描写",
"extension2":""
}
